{
  "active": true,
  "address": "0xe9e7CEA3DedcA5984780Bafc599bD69ADd087D56",
  "color": null,
  "decimals": 18,
  "description": {
    "en": "Binance-Peg BUSD (BUSD BEP20) is a token issued by Binance on Smart Chain; its price is pegged to BUSD (BUSD ERC20) at a ratio of 1:1."
  },
  "id": "9456bee8-7902-474a-8389-d5a033802436",
  "links": {
    "explorer": "https://bscscan.com/token/0xe9e7CEA3DedcA5984780Bafc599bD69ADd087D56",
    "research": "https://research.binance.com/en/projects/binance-usd",
    "website": "https://paxos.com/busd",
    "github": "https://github.com/binance-chain/",
    "twitter": "https://twitter.com/binance_dex",
    "blog": "https://binance.org/en/blog/",
    "telegram": "https://t.me/BinanceDEXchange",
    "coinmarketcap": "https://coinmarketcap.com/currencies/binance-usd/",
    "coingecko": "https://coingecko.com/en/coins/binance-usd/"
  },
  "logo": {
    "png": "https://raw.githubusercontent.com/map3xyz/assets/master/networks/smartchain/assets/smartchain-tokenlist/0xe9e7CEA3DedcA5984780Bafc599bD69ADd087D56/logo.png"
  },
  "name": "Binance-Peg BUSD",
  "networkCode": "smartchain",
  "spam": false,
  "symbol": "BUSD",
  "tags": [
    "binance-peg"
  ],
  "type": "asset",
  "verifications": [],
  "version": "0.0.1"
}