{
  "active": true,
  "address": "0x5d3AfBA1924aD748776E4Ca62213BF7acf39d773",
  "color": null,
  "decimals": 5,
  "description": {
    "en": "KGO is the Token of Kiwigo."
  },
  "id": "a797b33b-a18b-4327-8c7b-388672053819",
  "identifiers": {
    "coinmarketcap": 8877
  },
  "links": {
    "explorer": "https://bscscan.com/token/0x5d3afba1924ad748776e4ca62213bf7acf39d773",
    "research": "https://www.kiwigo.app/kgo-kiwigo-crypto-currency/",
    "website": "https://kiwigo.app"
  },
  "logo": {
    "png": "https://raw.githubusercontent.com/map3xyz/assets/master/networks/smartchain/assets/smartchain-tokenlist/0x5d3AfBA1924aD748776E4Ca62213BF7acf39d773/logo.png"
  },
  "name": "KIWIGO",
  "networkCode": "smartchain",
  "spam": false,
  "symbol": "KGO",
  "tags": [],
  "type": "asset",
  "verifications": [],
  "version": "0.0.1"
}