{
  "active": true,
  "address": "0x60322971a672B81BccE5947706D22c19dAeCf6Fb",
  "color": null,
  "decimals": 18,
  "description": {
    "en": "MarsDAO is a multifunctional decentralized platform designed for the use of crypto tools, which operates based on a DAO principle, on its native MDAO token."
  },
  "id": "67822605-36ab-43d1-8041-de394a522280",
  "links": {
    "explorer": "https://bscscan.com/token/0x60322971a672B81BccE5947706D22c19dAeCf6Fb",
    "website": "https://daomars.com",
    "twitter": "https://twitter.com/0xMarsDAO",
    "github": "https://github.com/MARS-DAO",
    "coingecko": "https://coingecko.com/coins/marsdao",
    "telegram": "https://t.me/MarsDAO_channel",
    "coinmarketcap": "https://coinmarketcap.com/currencies/marsdao/"
  },
  "logo": {
    "png": "https://raw.githubusercontent.com/map3xyz/assets/master/networks/smartchain/assets/smartchain-tokenlist/0x60322971a672B81BccE5947706D22c19dAeCf6Fb/logo.png"
  },
  "name": "MarsDAO",
  "networkCode": "smartchain",
  "spam": false,
  "symbol": "MDAO",
  "tags": [
    "deflationary"
  ],
  "type": "asset",
  "verifications": [],
  "version": "0.0.1"
}