{
  "active": true,
  "address": "0x8b303d5BbfBbf46F1a4d9741E491e06986894e18",
  "color": null,
  "decimals": 18,
  "description": {
    "en": "Woonkly Metasocial Network is a Decentralized Social Network where all posts are converted into NFTs directly, where users have full control of their data and where the content is not uploaded to a server but to users' computers through IPFS"
  },
  "id": "db4967e1-6c11-4dc0-9e78-8042e71f61ff",
  "links": {
    "explorer": "https://bscscan.com/token/0x8b303d5bbfbbf46f1a4d9741e491e06986894e18",
    "website": "https://woonkly.com",
    "coingecko": "https://coingecko.com/en/coins/woonkly-power",
    "facebook": "https://facebook.com/woonkly",
    "telegram": "https://t.me/woonkly",
    "twitter": "https://twitter.com/WoonklyEN",
    "youtube": "https://youtube.com/c/Woonkly",
    "medium": "https://woonkly.medium.com",
    "whitepaper": "https://whitepaper.woonkly.com/woonkly.com-eng/"
  },
  "logo": {
    "png": "https://raw.githubusercontent.com/map3xyz/smartchain-tokenlist/master/0x8b303d5BbfBbf46F1a4d9741E491e06986894e18/logo.png"
  },
  "name": "Woonkly Power",
  "networkCode": "smartchain",
  "spam": false,
  "symbol": "WOOP",
  "tags": [
    "defi"
  ],
  "type": "asset",
  "verifications": [],
  "version": "0.0.1"
}