{
  "active": true,
  "address": "0x8F1B7df4a34C8Dd072CF6408Be9c778CFABdf8D0",
  "color": null,
  "decimals": 18,
  "description": {
    "en": "IQ is a multi-chain (NeoScrypt and BEP-20) masternode cryptocurrency for Investors, Traders and Miners. Fork of DASH. Users can earn rewards with masternodes, benefiting the entire network and ecosysytem."
  },
  "id": "59f2c27c-ec44-4410-9281-17ebe4579008",
  "links": {
    "explorer": "https://bscscan.com/token/0x8F1B7df4a34C8Dd072CF6408Be9c778CFABdf8D0",
    "website": "https://IQ.cash/",
    "twitter": "https://twitter.com/IQ_crypto",
    "telegram": "https://t.me/IQ_cash",
    "discord": "https://discord.com/invite/qekuX6r",
    "facebook": "https://facebook.com/TradersFair/"
  },
  "logo": {
    "png": "https://raw.githubusercontent.com/map3xyz/assets/master/networks/smartchain/assets/smartchain-tokenlist/0x8F1B7df4a34C8Dd072CF6408Be9c778CFABdf8D0/logo.png"
  },
  "name": "Wrapped IQ.Cash",
  "networkCode": "smartchain",
  "spam": false,
  "symbol": "WIQ",
  "tags": [],
  "type": "asset",
  "verifications": [],
  "version": "0.0.1"
}