{
  "active": true,
  "address": "0x7C38870e93A1f959cB6c533eB10bBc3e438AaC11",
  "color": null,
  "decimals": 18,
  "description": {
    "en": "Alium Swap is a MultiChain Decentralized Exchange with a Cross-Chain option already operating on Binance Smart Chain and Huobi ECOChain with Ethereum, Near, Matic, Avalanche, Solana, and Tron coming."
  },
  "id": "216eaa08-ab91-43ec-9eb5-87b2a4a9f788",
  "links": {
    "explorer": "https://bscscan.com/token/0x7C38870e93A1f959cB6c533eB10bBc3e438AaC11",
    "website": "https://alium.finance/"
  },
  "logo": {
    "png": "https://raw.githubusercontent.com/map3xyz/smartchain-tokenlist/master/0x7C38870e93A1f959cB6c533eB10bBc3e438AaC11/logo.png"
  },
  "name": "AliumToken",
  "networkCode": "smartchain",
  "spam": false,
  "symbol": "ALM",
  "tags": [],
  "type": "asset",
  "verifications": [],
  "version": "0.0.1"
}